WebSonar/__init__.py
WebSonar/Common/Consts.py
WebSonar/Common/__init__.py
WebSonar/Common/Enums/SearchEngines.py
WebSonar/Common/Enums/WebsiteType.py
WebSonar/Common/Enums/__init__.py
WebSonar/Common/Exceptions/RetrievingSearchResultsException.py
WebSonar/Common/Exceptions/__init__.py
WebSonar/Discriminators/BaseDiscriminator.py
WebSonar/Discriminators/ShopifyDiscriminator.py
WebSonar/Discriminators/__init__.py
WebSonar/Engine/SonarEngine.py
WebSonar/Engine/__init__.py
WebSonar/SearchEnginesProvider/BaseSearchEngine.py
WebSonar/SearchEnginesProvider/GoogleEngine.py
WebSonar/SearchEnginesProvider/__init__.py
WebSonar-0.1.0.dist-info/METADATA
WebSonar-0.1.0.dist-info/WHEEL
WebSonar-0.1.0.dist-info/top_level.txt
WebSonar-0.1.0.dist-info/RECORD
