Metadata-Version: 2.1
Name: WebSonar
Version: 0.1.0
Summary: Describe your package in one sentence
Home-page: https://github.com/intv0id/WebSonar
Author: Clément Trassoudaine
Author-email: clement.trassoudaine@outlook.com
License: Apache License 2.0
Platform: UNKNOWN
Requires-Dist: beautifulsoup4
Requires-Dist: requests
